idlecloud/__init__.py
idlecloud/_version.py
idlecloud/py.typed
idlecloud-0.1.0.dist-info/licenses/LICENSE
idlecloud-0.1.0.dist-info/METADATA
idlecloud-0.1.0.dist-info/WHEEL
idlecloud-0.1.0.dist-info/top_level.txt
idlecloud-0.1.0.dist-info/RECORD
