Metadata-Version: 2.4
Name: idlecloud
Version: 0.1.0
Summary: Official Python SDK for IdleCloud - Decentralized AI inference on idle GPU infrastructure
Author-email: "IdleCloud, Inc." <alex@idlecloud.ai>
Maintainer-email: IdleCloud Engineering <alex@idlecloud.ai>
License: MIT
Project-URL: Homepage, https://idlecloud.ai
Project-URL: API Documentation, https://idlecloud.ai/docs
Project-URL: Get Access, https://idlecloud.ai
Project-URL: Issue Tracker, https://idlecloud.ai/support
Keywords: llm,ai,inference,gpt,openai-compatible,idlecloud,machine-learning,natural-language-processing
Classifier: Development Status :: 3 - Alpha
Classifier: Intended Audience :: Developers
Classifier: License :: OSI Approved :: MIT License
Classifier: Operating System :: OS Independent
Classifier: Programming Language :: Python :: 3
Classifier: Programming Language :: Python :: 3.8
Classifier: Programming Language :: Python :: 3.9
Classifier: Programming Language :: Python :: 3.10
Classifier: Programming Language :: Python :: 3.11
Classifier: Programming Language :: Python :: 3.12
Classifier: Topic :: Scientific/Engineering :: Artificial Intelligence
Classifier: Topic :: Software Development :: Libraries :: Python Modules
Classifier: Typing :: Typed
Requires-Python: >=3.8
License-File: LICENSE
Requires-Dist: openai>=1.0.0
Provides-Extra: dev
Requires-Dist: pytest>=7.0.0; extra == "dev"
Requires-Dist: pytest-asyncio>=0.21.0; extra == "dev"
Requires-Dist: python-dotenv>=1.0.0; extra == "dev"
Requires-Dist: build>=0.10.0; extra == "dev"
Dynamic: license-file
